{
  "detector": "IBDD",
  "dataset": "OutdoorObjects",
  "model": "HoeffdingTreeClassifier",
  "metric_code": "ACC_RT_REQL",
  "source_html": "IBDD_OutdoorObjects_HoeffdingTreeClassifier_ACCURACY-RUNTIME-REQLABELS.html",
  "overview": {
    "title": "Experiment overview",
    "columns": [
      "Setting",
      "Value"
    ],
    "rows": [
      [
        "Model for non-random steps",
        "SOBOL"
      ],
      [
        "Max. nr. evaluations (from arguments)",
        "50000"
      ],
      [
        "Number random steps",
        "50000"
      ],
      [
        "Number random steps (from arguments)",
        "20"
      ],
      [
        "Nr. of workers (parameter)",
        "30"
      ],
      [
        "Main process memory (GB)",
        "8"
      ],
      [
        "Worker memory (GB)",
        "64"
      ]
    ]
  },
  "parameters": {
    "title": "Experiment parameters",
    "columns": [
      "Name",
      "Type",
      "Lower bound",
      "Upper bound",
      "Values",
      "Type",
      "Log Scale?"
    ],
    "rows": [
      [
        "recent_samples_size",
        "int",
        "1",
        "5000",
        "",
        "int",
        "No"
      ],
      [
        "n_samples",
        "int",
        "1",
        "5000",
        "",
        "int",
        "No"
      ],
      [
        "n_permutations",
        "int",
        "2",
        "1000",
        "",
        "int",
        "No"
      ],
      [
        "update_interval",
        "int",
        "2",
        "250",
        "",
        "int",
        "No"
      ],
      [
        "n_consecutive_deviations",
        "int",
        "1",
        "250",
        "",
        "int",
        "No"
      ]
    ]
  }
}